Metadata-Version: 2.1
Name: yet-another-spotify-lyrics
Version: 2.4.5
Summary: Command Line Spotify Lyrics with Album Cover
Home-page: https://github.com/goktug97/yet-another-spotify-lyrics
Author: Göktuğ Karakaşlı
Author-email: karakasligk@gmail.com
License: MIT
Platform: UNKNOWN
Classifier: Programming Language :: Python :: 3
Classifier: License :: OSI Approved :: MIT License
Classifier: Operating System :: POSIX :: Linux
Requires-Python: >=3.6
License-File: LICENSE
